{
  "accounts": [
    [
      {
        "name": "1",
        "level": "13",
        "target_upgrade": "embassy",
        "target_research": ""
      },
      {
        "name": "2",
        "level": "13",
        "target_upgrade": "embassy",
        "target_research": ""
      }
    ],
    [
      {
        "name": "3",
        "level": "13",
        "target_upgrade": "embassy",
        "target_research": ""
      },
      {
        "name": "4",
        "level": "13",
        "target_upgrade": "embassy",
        "target_research": ""
      }
    ],
    [
      {
        "name": "5",
        "level": "13",
        "target_upgrade": "embassy",
        "target_research": ""
      },
      {
        "name": "6",
        "level": "13",
        "target_upgrade": "",
        "target_research": ""
      }
    ]
  ],
  "ruins_level_coordinate": {
    "x": 325,
    "y": 465
  },
  "recruit_frequency": 0,
  "sleep_interval": 3600,
  "interval_hour": 3,
  "vm_name": "AOZ_2",
  "vm_index": "2",
  "resource_level": 0
}
